readmetester/__init__.py
readmetester/__main__.py
readmetester/_assert.py
readmetester/_core.py
readmetester/_main.py
readmetester/_version.py
readmetester/exceptions.py
readmetester/py.typed
readmetester-2.4.1.dist-info/entry_points.txt
readmetester-2.4.1.dist-info/LICENSE
readmetester-2.4.1.dist-info/WHEEL
readmetester-2.4.1.dist-info/METADATA
readmetester-2.4.1.dist-info/RECORD
