Metadata-Version: 2.1
Name: readmetester
Version: 2.4.1
Summary: Parse, test, and assert RST code-blocks
Home-page: https://pypi.org/project/readmetester/
License: MIT
Keywords: assert,code,readme,rst,test
Author: jshwi
Author-email: stephen@jshwisolutions.com
Maintainer: jshwi
Maintainer-email: stephen@jshwisolutions.com
Requires-Python: >=3.8,<4.0
Classifier: License :: OSI Approved :: MIT License
Classifier: Programming Language :: Python :: 3
Classifier: Programming Language :: Python :: 3.8
Classifier: Programming Language :: Python :: 3.9
Classifier: Programming Language :: Python :: 3.10
Requires-Dist: Pygments (>=2.8.1,<3.0.0)
Requires-Dist: object-colors (>=2.0.0,<3.0.0)
Requires-Dist: pyproject-parser (>=0.4.3,<0.8.0)
Requires-Dist: restructuredtext-lint (>=1.4.0,<2.0.0)
Project-URL: Documentation, https://readmetester.readthedocs.io/en/latest
Project-URL: Repository, https://github.com/jshwi/readmetester
